License.txt
README.md
setup.py
GreenMatterAI/BatchLogger.py
GreenMatterAI/GreenMatterAI.py
GreenMatterAI/Utils.py
GreenMatterAI/__init__.py
GreenMatterAI.egg-info/PKG-INFO
GreenMatterAI.egg-info/SOURCES.txt
GreenMatterAI.egg-info/dependency_links.txt
GreenMatterAI.egg-info/requires.txt
GreenMatterAI.egg-info/top_level.txt