Metadata-Version: 2.1
Name: GreenMatterAI
Version: 0.0.19
Summary: GreenMatterAI's package
Author: GreenMatterAI
License-File: License.txt
